oembedpy/__init__.py
oembedpy/application.py
oembedpy/cli.py
oembedpy/consumer.py
oembedpy/discovery.py
oembedpy/provider.py
oembedpy/py.typed
oembedpy/types.py
oembedpy/adapters/__init__.py
oembedpy/adapters/mkdocs.py
oembedpy/adapters/sphinx.py
oembedpy/ext/__init__.py
oembedpy/ext/sphinx.py
oembedpy-0.9.0.dist-info/entry_points.txt
oembedpy-0.9.0.dist-info/licenses/LICENSE
oembedpy-0.9.0.dist-info/WHEEL
oembedpy-0.9.0.dist-info/METADATA
oembedpy-0.9.0.dist-info/RECORD
