Metadata-Version: 2.4
Name: oEmbedPy
Version: 0.9.0
Summary: oEmbed client for Python.
Author-email: Kazuya Takei <myself@attakei.net>
Requires-Python: >=3.9
Classifier: Development Status :: 4 - Beta
Classifier: Intended Audience :: Developers
Classifier: Environment :: Console
Classifier: Framework :: Sphinx
Classifier: Framework :: Sphinx :: Extension
Classifier: License :: OSI Approved :: Apache Software License
Classifier: Operating System :: OS Independent
Classifier: Programming Language :: Python :: 3 :: Only
Classifier: Programming Language :: Python :: 3.9
Classifier: Programming Language :: Python :: 3.10
Classifier: Programming Language :: Python :: 3.11
Classifier: Programming Language :: Python :: 3.12
Classifier: Programming Language :: Python :: 3.13
Classifier: Topic :: Documentation :: Sphinx
Classifier: Topic :: Internet
Classifier: Topic :: Internet :: WWW/HTTP
Classifier: Topic :: Utilities
License-File: LICENSE
Requires-Dist: beautifulsoup4
Requires-Dist: httpx
Requires-Dist: lxml
Requires-Dist: platformdirs
Requires-Dist: Click>=8 ; extra == "cli"
Requires-Dist: mkdocs>=1.4 ; extra == "mkdocs"
Requires-Dist: sphinx>=7 ; extra == "sphinx"
Project-URL: Documentation, https://oembedpy.readthedocs.io/en/v0.9.0/
Project-URL: Home, https://github.com/attakei/oEmbedPy
Provides-Extra: cli
Provides-Extra: mkdocs
Provides-Extra: sphinx
